hugbot/__init__.py
hugbot/main.py
hugbot/navigator.py
hugbot/utils.py
tests/__init__.py
tests/test_hugbot.py
HugBot-0.0.1.dist-info/LICENSE
HugBot-0.0.1.dist-info/METADATA
HugBot-0.0.1.dist-info/WHEEL
HugBot-0.0.1.dist-info/top_level.txt
HugBot-0.0.1.dist-info/RECORD
