Metadata-Version: 2.1
Name: HugBot
Version: 0.0.1
Summary: Automated interactions with Hugging Face Chat using Selenium
Home-page: https://github.com/chigwell/HugBot
Author: Eugene Evstafev
Author-email: chigwel@gmail.com
Classifier: Programming Language :: Python :: 3
Classifier: License :: OSI Approved :: MIT License
Classifier: Operating System :: OS Independent
Requires-Python: >=3.6
License-File: LICENSE
Requires-Dist: selenium
Requires-Dist: webdriver-manager
